mine_creater/__init__.py
mine_creater/mine_creater.py
mine_creater-0.0.13.dist-info/LICENSE
mine_creater-0.0.13.dist-info/METADATA
mine_creater-0.0.13.dist-info/WHEEL
mine_creater-0.0.13.dist-info/top_level.txt
mine_creater-0.0.13.dist-info/RECORD
